meditation_audio_generator/__init__.py
meditation_audio_generator/meditation_audio_generator.py
meditation_audio_generator/mp3_merger.py
meditation_audio_generator/mp3_mixer.py
meditation_audio_generator_openai-1.0.1.dist-info/METADATA
meditation_audio_generator_openai-1.0.1.dist-info/WHEEL
meditation_audio_generator_openai-1.0.1.dist-info/top_level.txt
meditation_audio_generator_openai-1.0.1.dist-info/RECORD
