Metadata-Version: 2.1
Name: meditation-audio-generator-openai
Version: 1.0.1
Summary: A tool to create guided audio meditations (like those found on YouTube but in audio-only form) using OpenAI.
Home-page: UNKNOWN
Author: Alexis Kirke
Author-email: alexiskirke2@gmail.com
License: UNKNOWN
Platform: UNKNOWN
Classifier: Programming Language :: Python :: 3
Classifier: License :: OSI Approved :: MIT License
Classifier: Operating System :: OS Independent
Requires-Python: >=3.6
Requires-Dist: pedalboard
Requires-Dist: pydub
Requires-Dist: openai
Requires-Dist: elevenlabs
